ncheck/__init__.py
ncheck/check.py
nagios_delivered-2023.8.30.post0.dist-info/LICENSE
nagios_delivered-2023.8.30.post0.dist-info/METADATA
nagios_delivered-2023.8.30.post0.dist-info/WHEEL
nagios_delivered-2023.8.30.post0.dist-info/top_level.txt
nagios_delivered-2023.8.30.post0.dist-info/RECORD
