Metadata-Version: 2.1
Name: nagios-delivered
Version: 2023.8.30.post0
Summary: A Package to Read Checks off of an S3 bucket rather than. Local Process
Author-email: Chris Halbersma <chris@halbersma.us>
Classifier: Programming Language :: Python :: 3
Classifier: Operating System :: OS Independent
Requires-Python: >=3.8
License-File: LICENSE
Requires-Dist: boto3
Requires-Dist: botocore
Requires-Dist: json-fix
